datatypes/converters.py
datatypes/datatypes.py
datatypes/io.py
datatypes/serializer.py
telekinesis_datatypes-0.0.1rc4.dist-info/licenses/LICENSE.txt
telekinesis_datatypes-0.0.1rc4.dist-info/METADATA
telekinesis_datatypes-0.0.1rc4.dist-info/WHEEL
telekinesis_datatypes-0.0.1rc4.dist-info/top_level.txt
telekinesis_datatypes-0.0.1rc4.dist-info/RECORD
