Metadata-Version: 2.4
Name: telekinesis-datatypes
Version: 0.0.1rc4
Summary: Official core data types and serialization utilities package for the Telekinesis SDK and APIs.
Author-email: Telekinesis <support@telekinesis.ai>
License-Expression: Apache-2.0
Project-URL: Homepage, https://telekinesis.ai
Project-URL: Documentation, https://docs.telekinesis.ai
Project-URL: Telekinesis Examples Repository, https://github.com/telekinesis-ai/telekinesis-examples
Classifier: Programming Language :: Python :: 3
Classifier: Programming Language :: Python :: 3.11
Classifier: Programming Language :: Python :: 3.12
Classifier: Operating System :: OS Independent
Classifier: Intended Audience :: Developers
Classifier: Topic :: Software Development :: Libraries
Requires-Python: <3.13,>=3.11
License-File: LICENSE.txt
Requires-Dist: pyarrow>=14.0.0
Requires-Dist: loguru>=0.5.3
Requires-Dist: numpy>=2.0
Requires-Dist: plyfile
Requires-Dist: trimesh
Dynamic: license-file
